setup.cfg
setup.py
brutius_slurmimus/__init__.py
brutius_slurmimus/jobs.py
brutius_slurmimus.egg-info/PKG-INFO
brutius_slurmimus.egg-info/SOURCES.txt
brutius_slurmimus.egg-info/dependency_links.txt
brutius_slurmimus.egg-info/entry_points.txt
brutius_slurmimus.egg-info/not-zip-safe
brutius_slurmimus.egg-info/top_level.txt