Metadata-Version: 1.0
Name: brutius-slurmimus
Version: 0.1.1dev
Summary: Parse-and-return slurm commands.  Don't use this.  Use pyslurm instead.
Home-page: http://github.com/ralphbean/brutius_slurmimus
Author: Ralph Bean
Author-email: ralph.bean@gmail.com
License: UNKNOWN
Platform: UNKNOWN
